MANIFEST.in
README.rst
setup.py
virtualenvwrapper/__init__.py
virtualenvwrapper/tryton_project.py
virtualenvwrapper.tryton.egg-info/PKG-INFO
virtualenvwrapper.tryton.egg-info/SOURCES.txt
virtualenvwrapper.tryton.egg-info/dependency_links.txt
virtualenvwrapper.tryton.egg-info/entry_points.txt
virtualenvwrapper.tryton.egg-info/namespace_packages.txt
virtualenvwrapper.tryton.egg-info/not-zip-safe
virtualenvwrapper.tryton.egg-info/top_level.txt