Metadata-Version: 1.1
Name: virtualenvwrapper.tryton
Version: 0.3
Summary: Tryton virtualenvwrapper plugin
Home-page: https://github.com/openlabs/virtualenvwrapper.tryton
Author: Openlabs
Author-email: support@openlabs.co.in
License: UNKNOWN
Platform: Any
Classifier: Development Status :: 3 - Alpha
Classifier: License :: OSI Approved :: BSD License
Classifier: Intended Audience :: Developers
Classifier: Environment :: Console
Classifier: Framework :: Django
Classifier: Programming Language :: Python :: 2
Classifier: Programming Language :: Python :: 2.6
Classifier: Programming Language :: Python :: 2.7
Requires: invoke
Requires: blessing
Requires: hgapi
Requires: virtualenv
Requires: virtualenvwrapper (>=4.0)
Provides: virtualenvwrapper.tryton
